magpack/__init__.py
magpack/_ovf_reader.py
magpack/image_utils.py
magpack/io.py
magpack/rotations.py
magpack/structures.py
magpack/vectorop.py
magpack-0.2.1.dist-info/licenses/LICENSE.txt
magpack-0.2.1.dist-info/METADATA
magpack-0.2.1.dist-info/WHEEL
magpack-0.2.1.dist-info/top_level.txt
magpack-0.2.1.dist-info/RECORD
