Metadata-Version: 2.4
Name: magpack
Version: 0.2.1
Summary: Tools for analysing 3D magnetic simulations and reconstructions
Author: Andreas Apseros
License-Expression: BSD-3-Clause
Project-URL: Homepage, https://github.com/apseros/magpack
Project-URL: Issues, https://github.com/apseros/magpack/issues
Classifier: Programming Language :: Python :: 3
Classifier: Intended Audience :: Science/Research
Classifier: Operating System :: OS Independent
Requires-Python: >=3.9
License-File: LICENSE.txt
Requires-Dist: numpy
Requires-Dist: pyevtk
Requires-Dist: matplotlib
Requires-Dist: pillow
Requires-Dist: scipy
Dynamic: license-file
